LICENSE.txt
MANIFEST.in
README.rst
setup.cfg
setup.py
bitfield/__init__.py
bitfield/walk.py
ctypes_bitfield.egg-info/PKG-INFO
ctypes_bitfield.egg-info/SOURCES.txt
ctypes_bitfield.egg-info/dependency_links.txt
ctypes_bitfield.egg-info/top_level.txt
remotestruct/__init__.py
remotestruct/cache.py
remotestruct/remotestruct.py
remotestruct/sparserange.py