Metadata-Version: 1.1
Name: ctypes-bitfield
Version: 0.3.3
Summary: Ctypes Register Bitfields
Home-page: https://github.com/NJDFan/ctypes-bitfield/
Author: Rob Gaddi
Author-email: rgaddi@highlandtechnology.com
License: MIT
Keywords: sample bitfield register memory
Platform: UNKNOWN
Classifier: Development Status :: 5 - Production/Stable
Classifier: Intended Audience :: Developers
Classifier: Topic :: System :: Hardware
Classifier: License :: OSI Approved :: MIT License
Classifier: Programming Language :: Python :: 2
Classifier: Programming Language :: Python :: 2.7
Classifier: Programming Language :: Python :: 3
Classifier: Programming Language :: Python :: 3.2
Classifier: Programming Language :: Python :: 3.3
Classifier: Programming Language :: Python :: 3.4
Classifier: Programming Language :: Python :: 3.5
Classifier: Programming Language :: Python :: 3.6
Classifier: Programming Language :: Python :: 3.7
Classifier: Programming Language :: Python :: 3.8
